circleci2/__init__.py
circleci2/api.py
circleci2/types.py
circleci2-0.1.1.dist-info/LICENSE
circleci2-0.1.1.dist-info/METADATA
circleci2-0.1.1.dist-info/WHEEL
circleci2-0.1.1.dist-info/RECORD
